wcgw/__init__.py
wcgw/py.typed
wcgw/types_.py
wcgw/client/__init__.py
wcgw/client/common.py
wcgw/client/diff-instructions.txt
wcgw/client/memory.py
wcgw/client/modes.py
wcgw/client/tool_prompts.py
wcgw/client/tools.py
wcgw/client/bash_state/bash_state.py
wcgw/client/bash_state/parser/__init__.py
wcgw/client/bash_state/parser/bash_statement_parser.py
wcgw/client/encoder/__init__.py
wcgw/client/file_ops/diff_edit.py
wcgw/client/file_ops/search_replace.py
wcgw/client/mcp_server/Readme.md
wcgw/client/mcp_server/__init__.py
wcgw/client/mcp_server/server.py
wcgw/client/repo_ops/display_tree.py
wcgw/client/repo_ops/file_stats.py
wcgw/client/repo_ops/path_prob.py
wcgw/client/repo_ops/paths_model.vocab
wcgw/client/repo_ops/paths_tokens.model
wcgw/client/repo_ops/repo_context.py
wcgw/relay/client.py
wcgw/relay/serve.py
wcgw/relay/static/privacy.txt
wcgw_cli/__init__.py
wcgw_cli/__main__.py
wcgw_cli/anthropic_client.py
wcgw_cli/cli.py
wcgw_cli/openai_client.py
wcgw_cli/openai_utils.py
wcgw_claudework1-4.1.2.dist-info/METADATA
wcgw_claudework1-4.1.2.dist-info/WHEEL
wcgw_claudework1-4.1.2.dist-info/entry_points.txt
wcgw_claudework1-4.1.2.dist-info/licenses/LICENSE
wcgw_claudework1-4.1.2.dist-info/RECORD
